LICENSE
MANIFEST.in
Pipfile
README.md
environment.yml
requirements.txt
setup.py
hifi/__init__,py
hifi/engine.py
hifi/hiphy.py
hifi/live-encoder.sh
hifi/out-ffmpeg.sh
hifi/test-encoder.sh
hifi/utils.py
hifi/vidsnatch.py
hifi/youtube-ffmpeg-mp4.sh
hifi.egg-info/PKG-INFO
hifi.egg-info/SOURCES.txt
hifi.egg-info/dependency_links.txt
hifi.egg-info/requires.txt
hifi.egg-info/top_level.txt
scripts/hifi
scripts/visbeats
visbeats/__init__.py
visbeats/adefines.py
visbeats/afilemanager.py
visbeats/afuncdict.py
visbeats/aimports.py
visbeats/aobject.py
visbeats/aparamdict.py
visbeats/audio.py
visbeats/audioclip.py
visbeats/event.py
visbeats/eventlist.py
visbeats/image.py
visbeats/image_cv.py
visbeats/mediafiles.py
visbeats/sourcelocationparser.py
visbeats/timesignal.py
visbeats/timesignal1d.py
visbeats/vbmidi.py
visbeats/vbobject.py
visbeats/video.py
visbeats/video_cv.py
visbeats/videoclip.py
visbeats/videosource.py
visbeats/visbeatdefines.py
visbeats/visbeatexamplevideo.py
visbeats/visbeatimports.py
visbeats/visualbeat.py
visbeats/warp.py
visbeats/assets/audio/hit.wav
visbeats/assets/images/VisBeatWatermark.png
visbeats/fileui/__init__.py
visbeats/fileui/uipath.py
visbeats/vbgui/__init__.py
visbeats/vbgui/beatgui.py